[{"name": "Amul Gold Full Cream Milk", "taxStatus": "taxable", "taxClass": "", "inStock": true, "stock": 2, "lowStockAmount": null, "salePrice": null, "regularPrice": 35, "categories": "Dairy Products"},
{"name": "Paras full cream milk", "taxStatus": "taxable", "taxClass": "", "inStock": false, "stock": null, "lowStockAmount": null, "salePrice": null, "regularPrice": 35, "categories": "Dairy Products"},
{"name": "Paras Dahi 380gm", "taxStatus": "taxable", "taxClass": "gst-5", "inStock": false, "stock": null, "lowStockAmount": null, "salePrice": null, "regularPrice": 32, "categories": "Dairy Products"},
{"name": "Ananda Delicious Dahi 160gm", "taxStatus": "taxable", "taxClass": "gst-5", "inStock": false, "stock": null, "lowStockAmount": null, "salePrice": null, "regularPrice": 20, "categories": "Dairy Products"},
{"name": "Ananda Delicious Dahi 330gm", "taxStatus": "taxable", "taxClass": "gst-5", "inStock": true, "stock": 1, "lowStockAmount": null, "salePrice": null, "regularPrice": 32, "categories": "Dairy Products"},
{"name": "Paras Dahi 175gm", "taxStatus": "taxable", "taxClass": "gst-5", "inStock": false, "stock": null, "lowStockAmount": null, "salePrice": null, "regularPrice": 19, "categories": "Dairy Products"},
{"name": "Paras Dahi 1kg", "taxStatus": "taxable", "taxClass": "gst-5", "inStock": true, "stock": 1, "lowStockAmount": null, "salePrice": null, "regularPrice": 78, "categories": "Dairy Products"},
{"name": "Ananda Paneer 180g", "taxStatus": "taxable", "taxClass": "gst-5", "inStock": true, "stock": 1, "lowStockAmount": null, "salePrice": null, "regularPrice": 84, "categories": "Dairy Products"},
{"name": "Amul butter 100g", "taxStatus": "taxable", "taxClass": "gst-5", "inStock": true, "stock": 1, "lowStockAmount": null, "salePrice": null, "regularPrice": 58, "categories": "Dairy Products"},
{"name": "Amul Cheese 200g (8 Cube x 25g)", "taxStatus": "taxable", "taxClass": "gst-5", "inStock": true, "stock": 1, "lowStockAmount": null, "salePrice": null, "regularPrice": 139, "categories": "Dairy Products"},
{"name": "Amul Blend Diced Cheese", "taxStatus": "taxable", "taxClass": "gst-5", "inStock": false, "stock": null, "lowStockAmount": null, "salePrice": null, "regularPrice": 129, "categories": "Dairy Products"},
{"name": "Amul Yummy Plain Cheese Spread  200g", "taxStatus": "taxable", "taxClass": "gst-5", "inStock": true, "stock": 1, "lowStockAmount": null, "salePrice": null, "regularPrice": 114, "categories": "Dairy Products"},
{"name": "Amul  Butter, 500 g", "taxStatus": "taxable", "taxClass": "gst-5", "inStock": false, "stock": null, "lowStockAmount": null, "salePrice": null, "regularPrice": 305, "categories": "Dairy Products"},
{"name": "Amul Mithai Mate Condensed Milk", "taxStatus": "taxable", "taxClass": "gst-5", "inStock": true, "stock": 1, "lowStockAmount": null, "salePrice": null, "regularPrice": 126, "categories": "Dairy Products"},
{"name": "Ananda Paneer Green 200g", "taxStatus": "taxable", "taxClass": "gst-5", "inStock": true, "stock": 1, "lowStockAmount": null, "salePrice": null, "regularPrice": 92, "categories": "Dairy Products"}]